open_af3/__init__.py
open_af3/constants.py
open_af3/diffusion.py
open_af3/model.py
open_af3/pairformer.py
open_af3/template_embedder.py
open_af3-0.0.8.dist-info/LICENSE
open_af3-0.0.8.dist-info/METADATA
open_af3-0.0.8.dist-info/WHEEL
open_af3-0.0.8.dist-info/RECORD
