Metadata-Version: 2.3
Name: open-af3
Version: 0.0.8
Summary: Paper - Pytorch
License: MIT
Keywords: artificial intelligence,deep learning,optimizers,Prompt Engineering
Author: Kye Gomez
Author-email: kye@apac.ai
Requires-Python: >=3.10,<4.0
Classifier: Development Status :: 4 - Beta
Classifier: Intended Audience :: Developers
Classifier: License :: OSI Approved :: MIT License
Classifier: Programming Language :: Python :: 3
Classifier: Programming Language :: Python :: 3.10
Classifier: Programming Language :: Python :: 3.11
Classifier: Programming Language :: Python :: 3.12
Classifier: Programming Language :: Python :: 3.13
Classifier: Programming Language :: Python :: 3.9
Classifier: Topic :: Scientific/Engineering :: Artificial Intelligence
Requires-Dist: einops
Requires-Dist: torch
Requires-Dist: zetascale
Project-URL: Documentation, https://github.com/kyegomez/AlphaFold3
Project-URL: Homepage, https://github.com/kyegomez/AlphaFold3
Project-URL: Repository, https://github.com/kyegomez/AlphaFold3
